flet_cli/cli.py
flet_cli/version.py
flet_cli/__pyinstaller/__init__.py
flet_cli/__pyinstaller/config.py
flet_cli/__pyinstaller/hook-flet.py
flet_cli/__pyinstaller/macos_utils.py
flet_cli/__pyinstaller/utils.py
flet_cli/__pyinstaller/win_utils.py
flet_cli/__pyinstaller/rthooks/pyi_rth_localhost_fletd.py
flet_cli/commands/base.py
flet_cli/commands/build.py
flet_cli/commands/build_base.py
flet_cli/commands/create.py
flet_cli/commands/debug.py
flet_cli/commands/devices.py
flet_cli/commands/doctor.py
flet_cli/commands/emulators.py
flet_cli/commands/flutter_base.py
flet_cli/commands/options.py
flet_cli/commands/pack.py
flet_cli/commands/publish.py
flet_cli/commands/run.py
flet_cli/commands/serve.py
flet_cli/utils/android_sdk.py
flet_cli/utils/distros.py
flet_cli/utils/flutter.py
flet_cli/utils/hash_stamp.py
flet_cli/utils/jdk.py
flet_cli/utils/merge.py
flet_cli/utils/processes.py
flet_cli/utils/project_dependencies.py
flet_cli/utils/pyproject_toml.py
flet_cli-0.80.0.dist-info/METADATA
flet_cli-0.80.0.dist-info/WHEEL
flet_cli-0.80.0.dist-info/entry_points.txt
flet_cli-0.80.0.dist-info/top_level.txt
flet_cli-0.80.0.dist-info/RECORD
