Metadata-Version: 2.4
Name: flet-cli
Version: 0.80.0
Summary: Flet CLI
Author-email: "Appveyor Systems Inc." <hello@flet.dev>
License-Expression: Apache-2.0
Project-URL: Homepage, https://flet.dev
Project-URL: Repository, https://github.com/flet-dev/flet
Project-URL: Documentation, https://flet.dev/docs
Requires-Python: >=3.10
Requires-Dist: flet
Requires-Dist: watchdog>=4.0.0
Requires-Dist: packaging>=25.0
Requires-Dist: qrcode>=7.4.2
Requires-Dist: tomli>=1.1.0; python_version < "3.11"
Requires-Dist: cookiecutter>=2.6.0
